{
  "title": "Language model-based document clustering using random walks",
  "url": "https://openalex.org/W1992795877",
  "year": 2006,
  "authors": [
    {
      "id": "https://openalex.org/A5030796190",
      "name": "Güneş Erkan",
      "affiliations": [
        "University of Michigan–Ann Arbor"
      ]
    },
    {
      "id": "https://openalex.org/A5030796190",
      "name": "Güneş Erkan",
      "affiliations": [
        "University of Michigan–Ann Arbor"
      ]
    }
  ],
  "references": [
    "https://openalex.org/W2283587406",
    "https://openalex.org/W2112090702",
    "https://openalex.org/W2130395434",
    "https://openalex.org/W2325227998",
    "https://openalex.org/W2793736636",
    "https://openalex.org/W1576676390",
    "https://openalex.org/W4234231991",
    "https://openalex.org/W2070412788",
    "https://openalex.org/W2100484636",
    "https://openalex.org/W2153390303",
    "https://openalex.org/W2034721576",
    "https://openalex.org/W2150384816",
    "https://openalex.org/W1514403774",
    "https://openalex.org/W2133576408",
    "https://openalex.org/W4249130062",
    "https://openalex.org/W1972594981",
    "https://openalex.org/W4231336072",
    "https://openalex.org/W1971318281",
    "https://openalex.org/W2434205482",
    "https://openalex.org/W4206765718",
    "https://openalex.org/W4255387915",
    "https://openalex.org/W2098034778",
    "https://openalex.org/W2141461755",
    "https://openalex.org/W2093390569",
    "https://openalex.org/W4235186159",
    "https://openalex.org/W1956559956",
    "https://openalex.org/W2950763224",
    "https://openalex.org/W2027875450",
    "https://openalex.org/W1991862576",
    "https://openalex.org/W2052819443",
    "https://openalex.org/W2066636486",
    "https://openalex.org/W3101913037",
    "https://openalex.org/W2146442558",
    "https://openalex.org/W2802074788",
    "https://openalex.org/W2165874743",
    "https://openalex.org/W2060314721",
    "https://openalex.org/W1525595230",
    "https://openalex.org/W2165469059"
  ],
  "abstract": "We propose a new document vector representation specifically designed for the document clustering task. Instead of the traditional term-based vectors, a document is represented as an n-dimensional vector, where n is the number of documents in the cluster. The value at each dimension of the vector is closely related to the generation probability based on the language model of the corresponding document. Inspired by the recent graph-based NLP methods, we reinforce the generation probabilities by iterating random walks on the underlying graph representation. Experiments with k-means and hierarchical clustering algorithms show significant improvements over the alternative tf·idf vector representation.",
  "full_text": null,
  "topic": "Cluster analysis",
  "concepts": [
    {
      "name": "Cluster analysis",
      "score": 0.7818751335144043
    },
    {
      "name": "Computer science",
      "score": 0.7050690054893494
    },
    {
      "name": "Random walk",
      "score": 0.5942088961601257
    },
    {
      "name": "Document clustering",
      "score": 0.5620940923690796
    },
    {
      "name": "Representation (politics)",
      "score": 0.5615931153297424
    },
    {
      "name": "Graph",
      "score": 0.5449627041816711
    },
    {
      "name": "Artificial intelligence",
      "score": 0.4980275630950928
    },
    {
      "name": "Dimension (graph theory)",
      "score": 0.4956401586532593
    },
    {
      "name": "Hierarchical clustering",
      "score": 0.432338148355484
    },
    {
      "name": "Theoretical computer science",
      "score": 0.3306560814380646
    },
    {
      "name": "Mathematics",
      "score": 0.21808436512947083
    },
    {
      "name": "Combinatorics",
      "score": 0.0983324646949768
    },
    {
      "name": "Statistics",
      "score": 0.07045477628707886
    },
    {
      "name": "Law",
      "score": 0.0
    },
    {
      "name": "Political science",
      "score": 0.0
    },
    {
      "name": "Politics",
      "score": 0.0
    }
  ]
}