{
    "title": "Predicting polymerization reactions via transfer learning using chemical language models",
    "url": "https://openalex.org/W4399322969",
    "year": 2024,
    "authors": [
        {
            "id": "https://openalex.org/A5104319626",
            "name": "Brenda S. Ferrari",
            "affiliations": [
                "IBM Research - Brazil"
            ]
        },
        {
            "id": "https://openalex.org/A2573726791",
            "name": "Matteo Manica",
            "affiliations": [
                "IBM Research - Zurich"
            ]
        },
        {
            "id": "https://openalex.org/A3018608913",
            "name": "Ronaldo Giro",
            "affiliations": [
                "IBM Research - Brazil"
            ]
        },
        {
            "id": "https://openalex.org/A2209038682",
            "name": "Teodoro Laino",
            "affiliations": [
                "IBM Research - Zurich",
                "Institute of Catalysis and Petrochemistry"
            ]
        },
        {
            "id": "https://openalex.org/A4220135265",
            "name": "Mathias B. Steiner",
            "affiliations": [
                "IBM Research - Brazil"
            ]
        },
        {
            "id": "https://openalex.org/A5104319626",
            "name": "Brenda S. Ferrari",
            "affiliations": []
        },
        {
            "id": "https://openalex.org/A2573726791",
            "name": "Matteo Manica",
            "affiliations": []
        },
        {
            "id": "https://openalex.org/A3018608913",
            "name": "Ronaldo Giro",
            "affiliations": []
        },
        {
            "id": "https://openalex.org/A2209038682",
            "name": "Teodoro Laino",
            "affiliations": []
        },
        {
            "id": "https://openalex.org/A4220135265",
            "name": "Mathias B. Steiner",
            "affiliations": []
        }
    ],
    "references": [
        "https://openalex.org/W3037654336",
        "https://openalex.org/W2625495882",
        "https://openalex.org/W4295791262",
        "https://openalex.org/W2883528235",
        "https://openalex.org/W3095028680",
        "https://openalex.org/W3091459767",
        "https://openalex.org/W3112510144",
        "https://openalex.org/W4385379602",
        "https://openalex.org/W4381510318",
        "https://openalex.org/W2137604422",
        "https://openalex.org/W3033186646",
        "https://openalex.org/W2075728943",
        "https://openalex.org/W3164174564",
        "https://openalex.org/W4386020939",
        "https://openalex.org/W4288435579",
        "https://openalex.org/W3178873356",
        "https://openalex.org/W4361284807",
        "https://openalex.org/W2038702914",
        "https://openalex.org/W2973074478",
        "https://openalex.org/W3129864870",
        "https://openalex.org/W3162823304",
        "https://openalex.org/W4211041253",
        "https://openalex.org/W2947423323",
        "https://openalex.org/W3010145447",
        "https://openalex.org/W6739901393",
        "https://openalex.org/W1964981516",
        "https://openalex.org/W1650728208",
        "https://openalex.org/W1968392598",
        "https://openalex.org/W2078409902",
        "https://openalex.org/W1998572303",
        "https://openalex.org/W2911857519",
        "https://openalex.org/W3166043447",
        "https://openalex.org/W2048567566",
        "https://openalex.org/W2123111312",
        "https://openalex.org/W2028620022",
        "https://openalex.org/W2026982792",
        "https://openalex.org/W2909063104",
        "https://openalex.org/W2895061638",
        "https://openalex.org/W6610918142",
        "https://openalex.org/W2095700073",
        "https://openalex.org/W3017260797",
        "https://openalex.org/W4299576998",
        "https://openalex.org/W2963212250",
        "https://openalex.org/W3103092523"
    ],
    "abstract": "Abstract Polymers are candidate materials for a wide range of sustainability applications such as carbon capture and energy storage. However, computational polymer discovery lacks automated analysis of reaction pathways and stability assessment through retro-synthesis. Here, we report an extension of transformer-based language models to polymerization for both reaction and retrosynthesis tasks. To that end, we have curated a polymerization dataset for vinyl polymers covering reactions and retrosynthesis for representative homo-polymers and co-polymers. Overall, we obtain a forward model Top-4 accuracy of 80% and a backward model Top-4 accuracy of 60%. We further analyze the model performance with representative polymerization examples and evaluate its prediction quality from a materials science perspective. To enable validation and reuse, we have made our models and data available in public repositories.",
    "full_text": null
}